Metadata-Version: 2.1
Name: django-bootstrap3-datetimepicker-rubgomez93
Version: 3.0.2
Summary: Bootstrap3 compatible datetimepicker for Django projects.
Home-page: https://github.com/rubgombar1/django-bootstrap3-datetimepicker
Author: Nakahara Kunihiko, Samuel Colvin
Author-email: nakahara.kunihiko@gmail.com, s@muelcolvin.com
Maintainer: Ruben Gomez
Maintainer-email: rubgomez93@gmail.com
License: Apache License 2.0
Platform: UNKNOWN
Classifier: Framework :: Django :: 1.10
Classifier: Framework :: Django :: 1.11
Classifier: Intended Audience :: Developers
Classifier: License :: OSI Approved :: Apache Software License
Classifier: Programming Language :: Python
Classifier: Programming Language :: Python :: 2
Classifier: Programming Language :: Python :: 3
Classifier: Operating System :: OS Independent
Classifier: Topic :: Software Development :: Libraries
Classifier: Topic :: Utilities
Classifier: Environment :: Web Environment
Classifier: Framework :: Django
